pyroll/sims_power_and_labour.py
pyroll_sims_power_and_labour-2.0.1.dist-info/METADATA
pyroll_sims_power_and_labour-2.0.1.dist-info/WHEEL
pyroll_sims_power_and_labour-2.0.1.dist-info/licenses/LICENSE
pyroll_sims_power_and_labour-2.0.1.dist-info/RECORD
