Metadata-Version: 2.3
Name: pyroll-sims-power-and-labour
Version: 2.0.1
Summary: Plugin for PyRolL providing the power and labour calculation after R. B. Sims.
Author-email: Christoph Renzing <christoph.renzing@imf.tu-freiberg.de>
License-Expression: BSD-3-Clause
License-File: LICENSE
Classifier: Intended Audience :: Manufacturing
Classifier: Intended Audience :: Science/Research
Classifier: Operating System :: OS Independent
Classifier: Topic :: Scientific/Engineering
Requires-Python: <4.0,>=3.9
Requires-Dist: pyroll-core~=2.1
Requires-Dist: pyroll-hitchcock-roll-flattening~=2.0.0
